setup.cfg
setup.py
lib/boaconstructor/__init__.py
lib/boaconstructor/core.py
lib/boaconstructor/utils.py
lib/boaconstructor.egg-info/PKG-INFO
lib/boaconstructor.egg-info/SOURCES.txt
lib/boaconstructor.egg-info/dependency_links.txt
lib/boaconstructor.egg-info/eager_resources.txt
lib/boaconstructor.egg-info/not-zip-safe
lib/boaconstructor.egg-info/top_level.txt
lib/boaconstructor/tests/__init__.py
lib/boaconstructor/tests/testboaconstructor.py