Metadata-Version: 1.0
Name: boaconstructor
Version: 0.3.0
Summary: The boacontructor is a templating library for *data*, i.e. templating for dictionaries.
Home-page: UNKNOWN
Author: Oisin Mulvihill
Author-email: oisin dot mulvihill a-t gmail d-ot com
License: Apache License v2.0
Platform: UNKNOWN
